flask_secure_admin/__init__.py
flask_secure_admin/blueprint.py
flask_secure_admin/secure_model_view.py
flask_secure_admin/security_sqlsoup_user_datastore.py
flask_secure_admin/str_representation.py
flask_secure_admin/templates.py
flask_secure_admin/utils.py
flask_secure_admin/templates/admin/master.html
flask_secure_admin/templates/security/_macros.html
flask_secure_admin/templates/security/_menu.html
flask_secure_admin/templates/security/_messages.html
flask_secure_admin/templates/security/login_user.html
flask_secure_admin-0.1.2.dist-info/METADATA
flask_secure_admin-0.1.2.dist-info/WHEEL
flask_secure_admin-0.1.2.dist-info/top_level.txt
flask_secure_admin-0.1.2.dist-info/RECORD
