Metadata-Version: 2.1
Name: flask-secure-admin
Version: 0.1.2
Summary: A bundling of flask-security and flask-admin with a bit of integration.
Home-page: https://github.com/me/myproject
Author: Brian Peterson
Author-email: bepetersondev@gmail.com
License: MIT
Platform: UNKNOWN
Classifier: License :: OSI Approved :: MIT License
Classifier: Programming Language :: Python
Classifier: Programming Language :: Python :: 3
Classifier: Programming Language :: Python :: 3.6
Classifier: Programming Language :: Python :: Implementation :: CPython
Classifier: Programming Language :: Python :: Implementation :: PyPy
Requires-Python: >=3.6.0
Requires-Dist: flask
Requires-Dist: flask-admin
Requires-Dist: flask-security
Requires-Dist: sqlalchemy
Requires-Dist: sqlsoup
